hsize/__init__.py
hsize/hsize.py
hsize/tests.py
hsize-0.0.2.dist-info/DESCRIPTION.rst
hsize-0.0.2.dist-info/METADATA
hsize-0.0.2.dist-info/RECORD
hsize-0.0.2.dist-info/WHEEL
hsize-0.0.2.dist-info/metadata.json
hsize-0.0.2.dist-info/top_level.txt
