Metadata-Version: 2.0
Name: hsize
Version: 0.0.2
Summary: Convert the size between human size and bytes on python3
Home-page: UNKNOWN
Author: micahel tsui
Author-email: bwangel.me@gmail.com
License: MIT License
Keywords: human,size
Platform: any
